README.rst
manual_requirements.txt
requirements.txt
setup.py
wordpress_oauth/__init__.py
wordpress_oauth.egg-info/PKG-INFO
wordpress_oauth.egg-info/SOURCES.txt
wordpress_oauth.egg-info/dependency_links.txt
wordpress_oauth.egg-info/requires.txt
wordpress_oauth.egg-info/top_level.txt